ssh_keyconv/__init__.py
ssh_keyconv/__main__.py
ssh_keyconv/cli.py
ssh_keyconv-0.9.0.dist-info/entry_points.txt
ssh_keyconv-0.9.0.dist-info/licenses/LICENSE
ssh_keyconv-0.9.0.dist-info/WHEEL
ssh_keyconv-0.9.0.dist-info/METADATA
ssh_keyconv-0.9.0.dist-info/RECORD
