Metadata-Version: 2.4
Name: ssh_keyconv
Version: 0.9.0
Summary: SSH Key Conversion Utility
Keywords: ssh,openssh,pem,der,pkcs8,private key
Author-email: Kris Hardy <hardyrk@gmail.com>
Requires-Python: >=3.12
License-Expression: MIT
Classifier: Development Status :: 5 - Production/Stable
Classifier: Environment :: Console
Classifier: Intended Audience :: System Administrators
Classifier: Natural Language :: English
Classifier: Operating System :: OS Independent
Classifier: Programming Language :: Python :: 3
Classifier: Topic :: Internet
Classifier: Topic :: Security
Classifier: Topic :: Security :: Cryptography
Classifier: Topic :: System :: Networking
Classifier: Topic :: System :: Systems Administration
Classifier: Topic :: Utilities
License-File: LICENSE
Requires-Dist: cryptography>=44.0
Project-URL: changelog, https://codeberg.org/lkm35t/ssh-keyconv/commits/branch/main
Project-URL: homepage, https://codeberg.org/lkm35t/ssh-keyconv
Project-URL: issues, https://codeberg.org/lkm35t/ssh-keyconv/issues
Project-URL: source, https://codeberg.org/lkm35t/ssh-keyconv/src/branch/main
